api_lambda/__init__.py
api_lambda/request.py
api_lambda/response.py
api_lambda/router.py
api_lambda_router-1.0.0.dist-info/METADATA
api_lambda_router-1.0.0.dist-info/WHEEL
api_lambda_router-1.0.0.dist-info/top_level.txt
api_lambda_router-1.0.0.dist-info/RECORD
