Metadata-Version: 2.4
Name: api-lambda-router
Version: 1.0.0
Summary: A lightweight, Flask-inspired routing framework for AWS Lambda functions
Author-email: Abdulkarim Essam <abdulkarim.essam@hotmail.com>
License: MIT
Project-URL: Homepage, https://github.com/abdulkarim-essam/api-lambda
Project-URL: Documentation, https://github.com/abdulkarim-essam/api-lambda#readme
Project-URL: Repository, https://github.com/abdulkarim-essam/api-lambda
Project-URL: Bug Tracker, https://github.com/abdulkarim-essam/api-lambda/issues
Project-URL: Changelog, https://github.com/abdulkarim-essam/api-lambda/blob/main/CHANGELOG.md
Classifier: Development Status :: 5 - Production/Stable
Classifier: Intended Audience :: Developers
Classifier: License :: OSI Approved :: MIT License
Classifier: Operating System :: OS Independent
Classifier: Programming Language :: Python :: 3
Classifier: Programming Language :: Python :: 3.8
Classifier: Programming Language :: Python :: 3.9
Classifier: Programming Language :: Python :: 3.10
Classifier: Programming Language :: Python :: 3.11
Classifier: Programming Language :: Python :: 3.12
Classifier: Framework :: AWS CDK
Classifier: Topic :: Internet :: WWW/HTTP :: HTTP Servers
Classifier: Topic :: Software Development :: Libraries :: Python Modules
Classifier: Topic :: System :: Networking
Requires-Python: >=3.8
Provides-Extra: dev
Requires-Dist: pytest>=7.0.0; extra == "dev"
Requires-Dist: pytest-cov>=4.0.0; extra == "dev"
Requires-Dist: black>=22.0.0; extra == "dev"
Requires-Dist: flake8>=5.0.0; extra == "dev"
Requires-Dist: mypy>=1.0.0; extra == "dev"
Requires-Dist: pre-commit>=2.20.0; extra == "dev"
Requires-Dist: bandit>=1.7.0; extra == "dev"
Requires-Dist: safety>=2.0.0; extra == "dev"
Provides-Extra: docs
Requires-Dist: mkdocs>=1.4.0; extra == "docs"
Requires-Dist: mkdocs-material>=8.5.0; extra == "docs"
Requires-Dist: mkdocstrings[python]>=0.19.0; extra == "docs"
